{
  "parent": "minecraft:bwt/placed_cauldron",
  "criteria": {
    "got_light_block": {
      "conditions": {
        "items": [
          {
            "items": "bwt:light_block"
          }
        ]
      },
      "trigger": "minecraft:inventory_changed"
    }
  },
  "display": {
    "background": "minecraft:textures/gui/advancements/backgrounds/adventure.png",
    "description": "Create a light block. To hemp, it might as well be the sun",
    "icon": {
      "count": 1,
      "id": "bwt:light_block"
    },
    "title": "Underground Grow Operation"
  },
  "requirements": [
    [
      "got_light_block"
    ]
  ],
  "sends_telemetry_event": true
}